Classfile /C:/Users/Administrator/Documents/Studium/Compilerbau/rustyJ/lib/tests/AssignedFields.class
  Last modified 29.05.2023; size 425 bytes
  SHA-256 checksum ce2d43253c59962ff82b674eaff618b5f65e7385d620fe44e86911adbc7a6646
  Compiled from "AssignedFields.java"
class AssignedFields
  minor version: 0
  major version: 64
  flags: (0x0020) ACC_SUPER
  this_class: #8                          // AssignedFields
  super_class: #2                         // java/lang/Object
  interfaces: 0, fields: 5, methods: 1, attributes: 1
Constant pool:
   #1 = Methodref          #2.#3          // java/lang/Object."<init>":()V
   #2 = Class              #4             // java/lang/Object
   #3 = NameAndType        #5:#6          // "<init>":()V
   #4 = Utf8               java/lang/Object
   #5 = Utf8               <init>
   #6 = Utf8               ()V
   #7 = Fieldref           #8.#9          // AssignedFields.x:I
   #8 = Class              #10            // AssignedFields
   #9 = NameAndType        #11:#12        // x:I
  #10 = Utf8               AssignedFields
  #11 = Utf8               x
  #12 = Utf8               I
  #13 = Fieldref           #8.#14         // AssignedFields.c:C
  #14 = NameAndType        #15:#16        // c:C
  #15 = Utf8               c
  #16 = Utf8               C
  #17 = String             #18            // Hello World
  #18 = Utf8               Hello World
  #19 = Fieldref           #8.#20         // AssignedFields.s:Ljava/lang/String;
  #20 = NameAndType        #21:#22        // s:Ljava/lang/String;
  #21 = Utf8               s
  #22 = Utf8               Ljava/lang/String;
  #23 = Fieldref           #8.#24         // AssignedFields.stringsCanBeNull:Ljava/lang/String;
  #24 = NameAndType        #25:#22        // stringsCanBeNull:Ljava/lang/String;
  #25 = Utf8               stringsCanBeNull
  #26 = Fieldref           #8.#27         // AssignedFields.b:Z
  #27 = NameAndType        #28:#29        // b:Z
  #28 = Utf8               b
  #29 = Utf8               Z
  #30 = Utf8               Code
  #31 = Utf8               LineNumberTable
  #32 = Utf8               SourceFile
  #33 = Utf8               AssignedFields.java
{
  int x;
    descriptor: I
    flags: (0x0000)

  char c;
    descriptor: C
    flags: (0x0000)

  java.lang.String s;
    descriptor: Ljava/lang/String;
    flags: (0x0000)

  java.lang.String stringsCanBeNull;
    descriptor: Ljava/lang/String;
    flags: (0x0000)

  boolean b;
    descriptor: Z
    flags: (0x0000)

  AssignedFields();
    descriptor: ()V
    flags: (0x0000)
    Code:
      stack=2, locals=1, args_size=1
         0: aload_0
         1: invokespecial #1                  // Method java/lang/Object."<init>":()V
         4: aload_0
         5: bipush        69
         7: putfield      #7                  // Field x:I
        10: aload_0
        11: bipush        120
        13: putfield      #13                 // Field c:C
        16: aload_0
        17: ldc           #17                 // String Hello World
        19: putfield      #19                 // Field s:Ljava/lang/String;
        22: aload_0
        23: aconst_null
        24: putfield      #23                 // Field stringsCanBeNull:Ljava/lang/String;
        27: aload_0
        28: iconst_1
        29: putfield      #26                 // Field b:Z
        32: return
      LineNumberTable:
        line 1: 0
        line 2: 4
        line 3: 10
        line 4: 16
        line 5: 22
        line 6: 27
}
SourceFile: "AssignedFields.java"
