Classfile /C:/Users/Administrator/Documents/Studium/Compilerbau/rustyJ/lib/tests/ComplexIf.class
  Last modified 29.05.2023; size 370 bytes
  SHA-256 checksum f041ef18afe8a94aa2a250960c923b76d4841f28a49bf9883413fe8ed53d7150
  Compiled from "ComplexIf-gen.java"
class ComplexIf
  minor version: 0
  major version: 64
  flags: (0x0020) ACC_SUPER
  this_class: #7                          // ComplexIf
  super_class: #2                         // java/lang/Object
  interfaces: 0, fields: 0, methods: 2, attributes: 1
Constant pool:
   #1 = Methodref          #2.#3          // java/lang/Object."<init>":()V
   #2 = Class              #4             // java/lang/Object
   #3 = NameAndType        #5:#6          // "<init>":()V
   #4 = Utf8               java/lang/Object
   #5 = Utf8               <init>
   #6 = Utf8               ()V
   #7 = Class              #8             // ComplexIf
   #8 = Utf8               ComplexIf
   #9 = Utf8               Code
  #10 = Utf8               LineNumberTable
  #11 = Utf8               f
  #12 = Utf8               (C)Z
  #13 = Utf8               StackMapTable
  #14 = Utf8               SourceFile
  #15 = Utf8               ComplexIf-gen.java
{
  ComplexIf();
    descriptor: ()V
    flags: (0x0000)
    Code:
      stack=1, locals=1, args_size=1
         0: aload_0
         1: invokespecial #1                  // Method java/lang/Object."<init>":()V
         4: return
      LineNumberTable:
        line 1: 0

  boolean f(char);
    descriptor: (C)Z
    flags: (0x0000)
    Code:
      stack=2, locals=2, args_size=2
         0: iload_1
         1: bipush        97
         3: if_icmpne     8
         6: iconst_1
         7: ireturn
         8: iload_1
         9: bipush        98
        11: if_icmpne     16
        14: iconst_0
        15: ireturn
        16: iload_1
        17: bipush        99
        19: if_icmpne     24
        22: iconst_1
        23: ireturn
        24: iload_1
        25: bipush        100
        27: if_icmpeq     36
        30: iload_1
        31: bipush        101
        33: if_icmpne     38
        36: iconst_0
        37: ireturn
        38: iload_1
        39: bipush        100
        41: if_icmpeq     50
        44: iload_1
        45: bipush        101
        47: if_icmpne     52
        50: iconst_1
        51: ireturn
        52: iconst_0
        53: ireturn
      LineNumberTable:
        line 3: 0
        line 4: 6
        line 6: 8
        line 7: 14
        line 9: 16
        line 10: 22
        line 12: 24
        line 13: 36
        line 15: 38
        line 16: 50
        line 18: 52
      StackMapTable: number_of_entries = 7
        frame_type = 8 /* same */
        frame_type = 7 /* same */
        frame_type = 7 /* same */
        frame_type = 11 /* same */
        frame_type = 1 /* same */
        frame_type = 11 /* same */
        frame_type = 1 /* same */
}
SourceFile: "ComplexIf-gen.java"
