Classfile /C:/Users/Administrator/Documents/Studium/Compilerbau/rustyJ/lib/tests/emptyMethod.class
  Last modified 29.05.2023; size 243 bytes
  SHA-256 checksum 46ac8d12cb2c73f6cb09f96f13c21696fe18df494346a60012a476b56a7e79ca
  Compiled from "emptyMethod-gen.java"
class emptyMethod
  minor version: 0
  major version: 64
  flags: (0x0020) ACC_SUPER
  this_class: #7                          // emptyMethod
  super_class: #2                         // java/lang/Object
  interfaces: 0, fields: 0, methods: 2, attributes: 1
Constant pool:
   #1 = Methodref          #2.#3          // java/lang/Object."<init>":()V
   #2 = Class              #4             // java/lang/Object
   #3 = NameAndType        #5:#6          // "<init>":()V
   #4 = Utf8               java/lang/Object
   #5 = Utf8               <init>
   #6 = Utf8               ()V
   #7 = Class              #8             // emptyMethod
   #8 = Utf8               emptyMethod
   #9 = Utf8               Code
  #10 = Utf8               LineNumberTable
  #11 = Utf8               f
  #12 = Utf8               SourceFile
  #13 = Utf8               emptyMethod-gen.java
{
  emptyMethod();
    descriptor: ()V
    flags: (0x0000)
    Code:
      stack=1, locals=1, args_size=1
         0: aload_0
         1: invokespecial #1                  // Method java/lang/Object."<init>":()V
         4: return
      LineNumberTable:
        line 1: 0

  void f();
    descriptor: ()V
    flags: (0x0000)
    Code:
      stack=0, locals=1, args_size=1
         0: return
      LineNumberTable:
        line 3: 0
}
SourceFile: "emptyMethod-gen.java"
