Classfile /C:/Users/Administrator/Documents/Studium/Compilerbau/rustyJ/lib/tests/Fib.class
  Last modified 28.05.2023; size 448 bytes
  SHA-256 checksum 1ea529885ea89bc75284d161a15c4582c246ff7f0abc232bc79ce45b5a9ab11b
  Compiled from "Fib-gen.java"
class Fib
  minor version: 0
  major version: 64
  flags: (0x0020) ACC_SUPER
  this_class: #8                          // Fib
  super_class: #2                         // java/lang/Object
  interfaces: 0, fields: 0, methods: 3, attributes: 1
Constant pool:
   #1 = Methodref          #2.#3          // java/lang/Object."<init>":()V
   #2 = Class              #4             // java/lang/Object
   #3 = NameAndType        #5:#6          // "<init>":()V
   #4 = Utf8               java/lang/Object
   #5 = Utf8               <init>
   #6 = Utf8               ()V
   #7 = Methodref          #8.#9          // Fib.rec:(I)I
   #8 = Class              #10            // Fib
   #9 = NameAndType        #11:#12        // rec:(I)I
  #10 = Utf8               Fib
  #11 = Utf8               rec
  #12 = Utf8               (I)I
  #13 = Utf8               Code
  #14 = Utf8               LineNumberTable
  #15 = Utf8               StackMapTable
  #16 = Utf8               iter
  #17 = Utf8               SourceFile
  #18 = Utf8               Fib-gen.java
{
  Fib();
    descriptor: ()V
    flags: (0x0000)
    Code:
      stack=1, locals=1, args_size=1
         0: aload_0
         1: invokespecial #1                  // Method java/lang/Object."<init>":()V
         4: return
      LineNumberTable:
        line 1: 0

  int rec(int);
    descriptor: (I)I
    flags: (0x0000)
    Code:
      stack=4, locals=2, args_size=2
         0: iload_1
         1: iconst_2
         2: if_icmpge     7
         5: iload_1
         6: ireturn
         7: aload_0
         8: iload_1
         9: iconst_1
        10: isub
        11: invokevirtual #7                  // Method rec:(I)I
        14: aload_0
        15: iload_1
        16: iconst_2
        17: isub
        18: invokevirtual #7                  // Method rec:(I)I
        21: iadd
        22: ireturn
      LineNumberTable:
        line 3: 0
        line 4: 5
        line 6: 7
      StackMapTable: number_of_entries = 1
        frame_type = 7 /* same */

  int iter(int);
    descriptor: (I)I
    flags: (0x0000)
    Code:
      stack=2, locals=6, args_size=2
         0: iload_1
         1: iconst_2
         2: if_icmpge     7
         5: iload_1
         6: ireturn
         7: iconst_0
         8: istore_2
         9: iconst_1
        10: istore_3
        11: iconst_1
        12: istore        4
        14: iload         4
        16: iload         4
        18: if_icmpge     40
        21: iload_3
        22: iload_2
        23: iadd
        24: istore        5
        26: iload_3
        27: istore_2
        28: iload         5
        30: istore_3
        31: iload         4
        33: iconst_1
        34: iadd
        35: istore        4
        37: goto          14
        40: iload_3
        41: ireturn
      LineNumberTable:
        line 10: 0
        line 11: 5
        line 14: 7
        line 16: 9
        line 18: 11
        line 19: 14
        line 21: 21
        line 22: 26
        line 23: 28
        line 24: 31
        line 25: 37
        line 26: 40
      StackMapTable: number_of_entries = 3
        frame_type = 7 /* same */
        frame_type = 254 /* append */
          offset_delta = 6
          locals = [ int, int, int ]
        frame_type = 25 /* same */
}
SourceFile: "Fib-gen.java"
