Classfile /C:/Users/Administrator/Documents/Studium/Compilerbau/rustyJ/lib/tests/Fields.class
  Last modified 29.05.2023; size 267 bytes
  SHA-256 checksum ae52ebec06bd120db935d2db223993376108cc6162d672be3ad5534829787ad9
  Compiled from "Fields.java"
class Fields
  minor version: 0
  major version: 64
  flags: (0x0020) ACC_SUPER
  this_class: #7                          // Fields
  super_class: #2                         // java/lang/Object
  interfaces: 0, fields: 4, methods: 1, attributes: 1
Constant pool:
   #1 = Methodref          #2.#3          // java/lang/Object."<init>":()V
   #2 = Class              #4             // java/lang/Object
   #3 = NameAndType        #5:#6          // "<init>":()V
   #4 = Utf8               java/lang/Object
   #5 = Utf8               <init>
   #6 = Utf8               ()V
   #7 = Class              #8             // Fields
   #8 = Utf8               Fields
   #9 = Utf8               x
  #10 = Utf8               I
  #11 = Utf8               b
  #12 = Utf8               Z
  #13 = Utf8               c
  #14 = Utf8               C
  #15 = Utf8               s
  #16 = Utf8               Ljava/lang/String;
  #17 = Utf8               Code
  #18 = Utf8               LineNumberTable
  #19 = Utf8               SourceFile
  #20 = Utf8               Fields.java
{
  int x;
    descriptor: I
    flags: (0x0000)

  boolean b;
    descriptor: Z
    flags: (0x0000)

  char c;
    descriptor: C
    flags: (0x0000)

  java.lang.String s;
    descriptor: Ljava/lang/String;
    flags: (0x0000)

  Fields();
    descriptor: ()V
    flags: (0x0000)
    Code:
      stack=1, locals=1, args_size=1
         0: aload_0
         1: invokespecial #1                  // Method java/lang/Object."<init>":()V
         4: return
      LineNumberTable:
        line 1: 0
}
SourceFile: "Fields.java"
