Classfile /C:/Users/Administrator/Documents/Studium/Compilerbau/rustyJ/lib/tests/IntFields.class
  Last modified 29.05.2023; size 220 bytes
  SHA-256 checksum cc10713e6dbca02ba7598514f79dbd96a5acdff70e67d6e8d8195f9d6f924bfc
  Compiled from "IntFields.java"
class IntFields
  minor version: 0
  major version: 64
  flags: (0x0020) ACC_SUPER
  this_class: #7                          // IntFields
  super_class: #2                         // java/lang/Object
  interfaces: 0, fields: 2, methods: 1, attributes: 1
Constant pool:
   #1 = Methodref          #2.#3          // java/lang/Object."<init>":()V
   #2 = Class              #4             // java/lang/Object
   #3 = NameAndType        #5:#6          // "<init>":()V
   #4 = Utf8               java/lang/Object
   #5 = Utf8               <init>
   #6 = Utf8               ()V
   #7 = Class              #8             // IntFields
   #8 = Utf8               IntFields
   #9 = Utf8               x
  #10 = Utf8               I
  #11 = Utf8               y
  #12 = Utf8               Code
  #13 = Utf8               LineNumberTable
  #14 = Utf8               SourceFile
  #15 = Utf8               IntFields.java
{
  int x;
    descriptor: I
    flags: (0x0000)

  int y;
    descriptor: I
    flags: (0x0000)

  IntFields();
    descriptor: ()V
    flags: (0x0000)
    Code:
      stack=1, locals=1, args_size=1
         0: aload_0
         1: invokespecial #1                  // Method java/lang/Object."<init>":()V
         4: return
      LineNumberTable:
        line 1: 0
}
SourceFile: "IntFields.java"
