Classfile /C:/Users/Administrator/Documents/Studium/Compilerbau/rustyJ/lib/tests/MethodCall.class
  Last modified 31.05.2023; size 884 bytes
  SHA-256 checksum 36f6253433d67cb591f95c40be737968335af556312b72f791cea73aef37897c
  Compiled from "MethodCall-gen.java"
class MethodCall
  minor version: 0
  major version: 64
  flags: (0x0020) ACC_SUPER
  this_class: #12                         // MethodCall
  super_class: #2                         // java/lang/Object
  interfaces: 0, fields: 0, methods: 4, attributes: 3
Constant pool:
   #1 = Methodref          #2.#3          // java/lang/Object."<init>":()V
   #2 = Class              #4             // java/lang/Object
   #3 = NameAndType        #5:#6          // "<init>":()V
   #4 = Utf8               java/lang/Object
   #5 = Utf8               <init>
   #6 = Utf8               ()V
   #7 = String             #8             // World
   #8 = Utf8               World
   #9 = String             #10            // Hello
  #10 = Utf8               Hello
  #11 = Methodref          #12.#13        // MethodCall.hello:()Ljava/lang/String;
  #12 = Class              #14            // MethodCall
  #13 = NameAndType        #15:#16        // hello:()Ljava/lang/String;
  #14 = Utf8               MethodCall
  #15 = Utf8               hello
  #16 = Utf8               ()Ljava/lang/String;
  #17 = Methodref          #12.#18        // MethodCall.world:()Ljava/lang/String;
  #18 = NameAndType        #19:#16        // world:()Ljava/lang/String;
  #19 = Utf8               world
  #20 = InvokeDynamic      #0:#21         // #0:makeConcatWithConstants:(Ljava/lang/String;Ljava/lang/String;)Ljava/lang/String;
  #21 = NameAndType        #22:#23        // makeConcatWithConstants:(Ljava/lang/String;Ljava/lang/String;)Ljava/lang/String;
  #22 = Utf8               makeConcatWithConstants
  #23 = Utf8               (Ljava/lang/String;Ljava/lang/String;)Ljava/lang/String;
  #24 = Utf8               Code
  #25 = Utf8               LineNumberTable
  #26 = Utf8               f
  #27 = Utf8               SourceFile
  #28 = Utf8               MethodCall-gen.java
  #29 = Utf8               BootstrapMethods
  #30 = MethodHandle       6:#31          // REF_invokeStatic java/lang/invoke/StringConcatFactory.makeConcatWithConstants:(Ljava/lang/invoke/MethodHandles$Lookup;Ljava/lang/String;Ljava/lang/invoke/MethodType;Ljava/lang/String;[Ljava/lang/Object;)Ljava/lang/invoke/CallSite;
  #31 = Methodref          #32.#33        // java/lang/invoke/StringConcatFactory.makeConcatWithConstants:(Ljava/lang/invoke/MethodHandles$Lookup;Ljava/lang/String;Ljava/lang/invoke/MethodType;Ljava/lang/String;[Ljava/lang/Object;)Ljava/lang/invoke/CallSite;
  #32 = Class              #34            // java/lang/invoke/StringConcatFactory
  #33 = NameAndType        #22:#35        // makeConcatWithConstants:(Ljava/lang/invoke/MethodHandles$Lookup;Ljava/lang/String;Ljava/lang/invoke/MethodType;Ljava/lang/String;[Ljava/lang/Object;)Ljava/lang/invoke/CallSite;
  #34 = Utf8               java/lang/invoke/StringConcatFactory
  #35 = Utf8               (Ljava/lang/invoke/MethodHandles$Lookup;Ljava/lang/String;Ljava/lang/invoke/MethodType;Ljava/lang/String;[Ljava/lang/Object;)Ljava/lang/invoke/CallSite;
  #36 = String             #37            // \u0001 \u0001
  #37 = Utf8               \u0001 \u0001
  #38 = Utf8               InnerClasses
  #39 = Class              #40            // java/lang/invoke/MethodHandles$Lookup
  #40 = Utf8               java/lang/invoke/MethodHandles$Lookup
  #41 = Class              #42            // java/lang/invoke/MethodHandles
  #42 = Utf8               java/lang/invoke/MethodHandles
  #43 = Utf8               Lookup
{
  MethodCall();
    descriptor: ()V
    flags: (0x0000)
    Code:
      stack=1, locals=1, args_size=1
         0: aload_0
         1: invokespecial #1                  // Method java/lang/Object."<init>":()V
         4: return
      LineNumberTable:
        line 1: 0

  java.lang.String world();
    descriptor: ()Ljava/lang/String;
    flags: (0x0000)
    Code:
      stack=1, locals=1, args_size=1
         0: ldc           #7                  // String World
         2: areturn
      LineNumberTable:
        line 3: 0

  java.lang.String hello();
    descriptor: ()Ljava/lang/String;
    flags: (0x0000)
    Code:
      stack=1, locals=1, args_size=1
         0: ldc           #9                  // String Hello
         2: areturn
      LineNumberTable:
        line 6: 0

  java.lang.String f();
    descriptor: ()Ljava/lang/String;
    flags: (0x0000)
    Code:
      stack=2, locals=1, args_size=1
         0: aload_0
         1: invokevirtual #11                 // Method hello:()Ljava/lang/String;
         4: aload_0
         5: invokevirtual #17                 // Method world:()Ljava/lang/String;
         8: invokedynamic #20,  0             // InvokeDynamic #0:makeConcatWithConstants:(Ljava/lang/String;Ljava/lang/String;)Ljava/lang/String;
        13: areturn
      LineNumberTable:
        line 9: 0
}
SourceFile: "MethodCall-gen.java"
BootstrapMethods:
  0: #30 REF_invokeStatic java/lang/invoke/StringConcatFactory.makeConcatWithConstants:(Ljava/lang/invoke/MethodHandles$Lookup;Ljava/lang/String;Ljava/lang/invoke/MethodType;Ljava/lang/String;[Ljava/lang/Object;)Ljava/lang/invoke/CallSite;
    Method arguments:
      #36 \u0001 \u0001
InnerClasses:
  public static final #43= #39 of #41;    // Lookup=class java/lang/invoke/MethodHandles$Lookup of class java/lang/invoke/MethodHandles
